decades/__init__.py
decades/__main__.py
decades/main.py
decades-0.1.0.dist-info/LICENSE
decades-0.1.0.dist-info/METADATA
decades-0.1.0.dist-info/WHEEL
decades-0.1.0.dist-info/entry_points.txt
decades-0.1.0.dist-info/RECORD
