Metadata-Version: 2.1
Name: decades
Version: 0.1.0
Summary: A CLI tool to save recovery snapshots of your projects or files. ⌚
License: MIT
Author: Adam Garza
Author-email: 168875175+hyerland@users.noreply.github.com
Requires-Python: >=3.8,<4.0
Classifier: License :: OSI Approved :: MIT License
Classifier: Programming Language :: Python :: 3
Classifier: Programming Language :: Python :: 3.8
Classifier: Programming Language :: Python :: 3.9
Classifier: Programming Language :: Python :: 3.10
Classifier: Programming Language :: Python :: 3.11
Classifier: Programming Language :: Python :: 3.12
Requires-Dist: typer[all] (>=0.12.3,<0.13.0)
